dreipc_python/__init__.py
dreipc_python/cli.py
dreipc_python/generator.py
dreipc_python-1.0.6.dist-info/METADATA
dreipc_python-1.0.6.dist-info/WHEEL
dreipc_python-1.0.6.dist-info/entry_points.txt
dreipc_python-1.0.6.dist-info/licenses/LICENSE
dreipc_python-1.0.6.dist-info/RECORD
