Metadata-Version: 2.4
Name: dreipc-python
Version: 1.0.6
Summary: A simple CLI tool for creating FastAPI projects for 3pc
Author-email: Elyess Eleuch <eeleuch@3pc.de>
License-Expression: MIT
License-File: LICENSE
Keywords: cli,dependency-injection,fastapi,python,template
Classifier: Development Status :: 4 - Beta
Classifier: Environment :: Console
Classifier: Framework :: FastAPI
Classifier: Intended Audience :: Developers
Classifier: License :: OSI Approved :: MIT License
Classifier: Operating System :: OS Independent
Classifier: Programming Language :: Python :: 3
Classifier: Programming Language :: Python :: 3.8
Classifier: Programming Language :: Python :: 3.9
Classifier: Programming Language :: Python :: 3.10
Classifier: Programming Language :: Python :: 3.11
Classifier: Programming Language :: Python :: 3.12
Classifier: Programming Language :: Python :: 3.13
Classifier: Topic :: Software Development :: Code Generators
Requires-Python: >=3.8
Requires-Dist: click>=8.0.0
Requires-Dist: rich>=12.0.0
Provides-Extra: dev
Requires-Dist: black>=22.0.0; extra == 'dev'
Requires-Dist: flake8>=5.0.0; extra == 'dev'
Requires-Dist: isort>=5.0.0; extra == 'dev'
Requires-Dist: mypy>=1.0.0; extra == 'dev'
Requires-Dist: pytest-cov>=4.0.0; extra == 'dev'
Requires-Dist: pytest>=7.0.0; extra == 'dev'
